{
"type": "FeatureCollection",
"name": "story",
"crs": { "type": "name", "properties": { "name": "urn:ogc:def:crs:OGC:1.3:CRS84" } },
"features": [
{ "type": "Feature", "properties": { "id": 1 }, "geometry": { "type": "Point", "coordinates": [ -0.409381559243575, 50.818404289657316 ] } },
{ "type": "Feature", "properties": { "id": 2 }, "geometry": { "type": "Point", "coordinates": [ 0.905049953857077, 51.891832127002672 ] } },
{ "type": "Feature", "properties": { "id": 3 }, "geometry": { "type": "Point", "coordinates": [ -0.123669040736242, 51.509156278865845 ] } },
{ "type": "Feature", "properties": { "id": 4 }, "geometry": { "type": "Point", "coordinates": [ -2.591380939277481, 51.459866466491292 ] } }
]
}
